{
  "attributes": [
    {
      "allow_nil?": false,
      "default": "nil",
      "generated?": true,
      "primary_key?": true,
      "references": null,
      "size": null,
      "source": "id",
      "type": "bigint"
    },
    {
      "allow_nil?": false,
      "default": "nil",
      "generated?": false,
      "primary_key?": false,
      "references": null,
      "size": null,
      "source": "name",
      "type": "text"
    },
    {
      "allow_nil?": false,
      "default": "\"expense\"",
      "generated?": false,
      "primary_key?": false,
      "references": null,
      "size": null,
      "source": "type",
      "type": "text"
    },
    {
      "allow_nil?": false,
      "default": "fragment(\"(now() AT TIME ZONE 'utc')\")",
      "generated?": false,
      "primary_key?": false,
      "references": null,
      "size": null,
      "source": "inserted_at",
      "type": "utc_datetime_usec"
    },
    {
      "allow_nil?": false,
      "default": "fragment(\"(now() AT TIME ZONE 'utc')\")",
      "generated?": false,
      "primary_key?": false,
      "references": null,
      "size": null,
      "source": "updated_at",
      "type": "utc_datetime_usec"
    },
    {
      "allow_nil?": true,
      "default": "nil",
      "generated?": false,
      "primary_key?": false,
      "references": {
        "deferrable": false,
        "destination_attribute": "id",
        "destination_attribute_default": null,
        "destination_attribute_generated": null,
        "index?": false,
        "match_type": null,
        "match_with": null,
        "multitenancy": {
          "attribute": null,
          "global": null,
          "strategy": null
        },
        "name": "categories_parent_id_fkey",
        "on_delete": null,
        "on_update": null,
        "primary_key?": true,
        "schema": "public",
        "table": "categories"
      },
      "size": null,
      "source": "parent_id",
      "type": "bigint"
    }
  ],
  "base_filter": null,
  "check_constraints": [],
  "custom_indexes": [],
  "custom_statements": [],
  "has_create_action": true,
  "hash": "135AB85160B24A52B1901831B26D42D92E45109CCDDF9F9844EDE3D961B6B869",
  "identities": [],
  "multitenancy": {
    "attribute": null,
    "global": null,
    "strategy": null
  },
  "repo": "Elixir.HousekeepingBook.Repo",
  "schema": null,
  "table": "categories"
}